odoo/addons/l10n_br_repair/README.rst
odoo/addons/l10n_br_repair/__init__.py
odoo/addons/l10n_br_repair/__manifest__.py
odoo/addons/l10n_br_repair/data/res_company.xml
odoo/addons/l10n_br_repair/demo/repair_order.xml
odoo/addons/l10n_br_repair/demo/res_company.xml
odoo/addons/l10n_br_repair/i18n/l10n_br_repair.pot
odoo/addons/l10n_br_repair/i18n/pt_BR.po
odoo/addons/l10n_br_repair/migrations/12.0.2.0.0/pre-migration.py
odoo/addons/l10n_br_repair/migrations/12.0.2.1.0/pre-migration.py
odoo/addons/l10n_br_repair/models/__init__.py
odoo/addons/l10n_br_repair/models/fiscal_line_mixin.py
odoo/addons/l10n_br_repair/models/repair_fee.py
odoo/addons/l10n_br_repair/models/repair_line.py
odoo/addons/l10n_br_repair/models/repair_order.py
odoo/addons/l10n_br_repair/models/res_company.py
odoo/addons/l10n_br_repair/models/res_config_settings.py
odoo/addons/l10n_br_repair/readme/CONFIGURE.rst
odoo/addons/l10n_br_repair/readme/CONTRIBUTORS.rst
odoo/addons/l10n_br_repair/readme/CREDITS.rst
odoo/addons/l10n_br_repair/readme/DESCRIPTION.rst
odoo/addons/l10n_br_repair/readme/HISTORY.rst
odoo/addons/l10n_br_repair/readme/INSTALL.rst
odoo/addons/l10n_br_repair/readme/ROADMAP.rst
odoo/addons/l10n_br_repair/readme/USAGE.rst
odoo/addons/l10n_br_repair/report/repair_templates_repair_order.xml
odoo/addons/l10n_br_repair/security/l10n_br_repair_security.xml
odoo/addons/l10n_br_repair/static/description/banner.png
odoo/addons/l10n_br_repair/static/description/icon.png
odoo/addons/l10n_br_repair/static/description/index.html
odoo/addons/l10n_br_repair/tests/__init__.py
odoo/addons/l10n_br_repair/tests/test_l10n_br_repair.py
odoo/addons/l10n_br_repair/tests/test_l10n_br_repair_lc.py
odoo/addons/l10n_br_repair/tests/test_l10n_br_repair_sn.py
odoo/addons/l10n_br_repair/views/repair_fee.xml
odoo/addons/l10n_br_repair/views/repair_line.xml
odoo/addons/l10n_br_repair/views/repair_order.xml
odoo/addons/l10n_br_repair/views/res_company.xml
odoo12_addon_l10n_br_repair-12.0.9.0.0.dist-info/METADATA
odoo12_addon_l10n_br_repair-12.0.9.0.0.dist-info/WHEEL
odoo12_addon_l10n_br_repair-12.0.9.0.0.dist-info/top_level.txt
odoo12_addon_l10n_br_repair-12.0.9.0.0.dist-info/RECORD
