Metadata-Version: 2.1
Name: odoo12-addon-l10n-br-repair
Version: 12.0.9.0.0
Summary: Brazilian Localization Repair
Home-page: https://github.com/OCA/l10n-brazil
Author: Escodoo, Odoo Community Association (OCA)
Author-email: support@odoo-community.org
License: AGPL-3
Platform: UNKNOWN
Classifier: Programming Language :: Python
Classifier: Framework :: Odoo
Classifier: Framework :: Odoo :: 12.0
Classifier: License :: OSI Approved :: GNU Affero General Public License v3
Classifier: Development Status :: 3 - Alpha
Requires-Python: >=3.5
Requires-Dist: odoo12-addon-l10n-br-stock-account
Requires-Dist: odoo12-addon-repair-payment-term
Requires-Dist: odoo (<12.1dev,>=12.0a)
